topogenesis/__init__.py
topogenesis/data.py
topogenesis/other.py
topogenesis/datastructures/__init__.py
topogenesis/datastructures/datastructures.py
topogenesis/datastructures/sfunc.py
topogenesis/datastructures/utilities.py
topogenesis/geometry/__init__.py
topogenesis/geometry/load.py
topogenesis/geometry/sampling.py
topogenesis-0.0.13.dist-info/LICENSE
topogenesis-0.0.13.dist-info/METADATA
topogenesis-0.0.13.dist-info/WHEEL
topogenesis-0.0.13.dist-info/top_level.txt
topogenesis-0.0.13.dist-info/RECORD
